<COMPONENT>
	<HEADER PLATEFORM="ALL" SERIAL="" VERSION="0.102" STATUS="ALPHA"
		COMPATIBILITY="ALL" AUTHOR="Talend" RELEASE_DATE="20090320A"
		STARTABLE="false" PARTITIONING="NONE" LOG4J_ENABLED="true">
		<SIGNATURE />
	</HEADER>

  <FAMILIES>
    <FAMILY>Processing/Hadoop</FAMILY>
	<FAMILY>Big Data/Pig</FAMILY>
  </FAMILIES>

	<DOCUMENTATION>
		<URL />
	</DOCUMENTATION>

	<CONNECTORS>
		<CONNECTOR CTYPE="FLOW" MAX_OUTPUT="0" MAX_INPUT="1" />
		<CONNECTOR NAME="PIGCOMBINE" CTYPE="FLOW" MAX_INPUT="1" MAX_OUTPUT="1" COLOR="086438" BASE_SCHEMA="FLOW"/>
	</CONNECTORS>

	<PARAMETERS>
		<PARAMETER NAME="SCHEMA" FIELD="SCHEMA_TYPE" REQUIRED="true" NUM_ROW="1"/>
		<PARAMETER NAME="SCHEMA_COMBINE" FIELD="SCHEMA_TYPE" REQUIRED="true" NUM_ROW="1" CONTEXT="PIGCOMBINE"/>

		<PARAMETER NAME="CROSS_FILENAME" FIELD="FILE" NUM_ROW="20"
			REQUIRED="true">
			<DEFAULT>"__COMP_DEFAULT_FILE_DIR__/in.csv"</DEFAULT>
		</PARAMETER>

		<PARAMETER NAME="FIELD_SEPARATOR_CHAR" FIELD="TEXT" NUM_ROW="30"
			REQUIRED="true">
			<DEFAULT>";"</DEFAULT>
		</PARAMETER>
	</PARAMETERS>

	<ADVANCED_PARAMETERS>

		<PARAMETER NAME="USE_PARTITION" FIELD="CHECK" REQUIRED="true" NUM_ROW="20">
			<DEFAULT>false</DEFAULT>
		</PARAMETER>

		<PARAMETER NAME="PARTITION" FIELD="TEXT" NUM_ROW="20" REQUIRED="true" SHOW_IF="USE_PARTITION == 'true'">
			<DEFAULT>"org.apache.pig.test.SimpleCustomPartitioner"</DEFAULT>
		</PARAMETER>

		<PARAMETER NAME="INCREASE_PARALLELISM" FIELD="CHECK" REQUIRED="true" NUM_ROW="30">
			<DEFAULT>false</DEFAULT>
		</PARAMETER>

		<PARAMETER NAME="REDUCE_NUMBER" FIELD="TEXT" REQUIRED="true" NUM_ROW="30" SHOW_IF="INCREASE_PARALLELISM == 'true'">
			<DEFAULT>2</DEFAULT>
		</PARAMETER>
	</ADVANCED_PARAMETERS>

	<CODEGENERATION>
	</CODEGENERATION>
	<RETURNS />

</COMPONENT>
