<COMPONENT>

  <HEADER
    PLATEFORM="ALL"
    SERIAL=""
    VERSION="0.102"
    STATUS="ALPHA"

    COMPATIBILITY="ALL"
    AUTHOR="Talend"
    RELEASE_DATE="20120802A"
    STARTABLE="false"
  >
    <SIGNATURE/>
  </HEADER>

  <FAMILIES>
    <FAMILY>ELT/Map/Hive</FAMILY>
  </FAMILIES>

  <DOCUMENTATION>
    <URL/>
  </DOCUMENTATION>

  <CONNECTORS>
    <CONNECTOR CTYPE="TABLE" MAX_INPUT="0"/>
    <CONNECTOR CTYPE="FLOW" MAX_INPUT="0" MAX_OUTPUT="0"/>
    <CONNECTOR CTYPE="SUBJOB_OK" MAX_INPUT="1" />
    <CONNECTOR CTYPE="SUBJOB_ERROR" MAX_INPUT="1" />
    <CONNECTOR CTYPE="COMPONENT_OK"/>
    <CONNECTOR CTYPE="COMPONENT_ERROR"/>
    <CONNECTOR CTYPE="RUN_IF"/>
  </CONNECTORS>

  <PARAMETERS>

    <PARAMETER
      NAME="SCHEMA"
      FIELD="SCHEMA_TYPE"
      NUM_ROW="5"
    >
      <DEFAULT>''</DEFAULT>
    </PARAMETER>

    <PARAMETER
      NAME="ELT_TABLE_NAME"
      FIELD="TEXT"
      NUM_ROW="6"
    >
      <DEFAULT>""</DEFAULT>
    </PARAMETER>

    <PARAMETER
      NAME="ELT_SCHEMA_NAME"
      FIELD="TEXT"
      NUM_ROW="7"
    >
      <DEFAULT>""</DEFAULT>
    </PARAMETER>

    <PARAMETER
      NAME="MAPPING"
      FIELD="MAPPING_TYPE"
      NUM_ROW="99"
      SHOW="true"
      READONLY="true"
    >
      <DEFAULT>hive_id</DEFAULT>
    </PARAMETER>

   </PARAMETERS>

   <CODEGENERATION>
   </CODEGENERATION>

   <RETURNS>
   </RETURNS>
</COMPONENT>