<COMPONENT>
	<HEADER PLATEFORM="ALL" SERIAL="" VERSION="0.102" STATUS="ALPHA"
		COMPATIBILITY="ALL" AUTHOR="Talend" RELEASE_DATE="20070314A"
		STARTABLE="true" SUPPORTS_DB_TYPE="true" HAS_CONDITIONAL_OUTPUTS="true">
		<SIGNATURE />
	</HEADER>
	<FAMILIES>
		<FAMILY>Big Data/Impala</FAMILY>
	</FAMILIES>
	<DOCUMENTATION>
		<URL />
	</DOCUMENTATION>
	<CONNECTORS>
		<CONNECTOR CTYPE="FLOW" MAX_INPUT="1" MAX_OUTPUT="1" />
		<CONNECTOR NAME="REJECT" CTYPE="FLOW" MAX_INPUT="0"
			MAX_OUTPUT="1" LINE_STYLE="2" COLOR="FF0000" BASE_SCHEMA="FLOW"
			NOT_SHOW_IF="(DATA_ACTION == 'INSERT' OR DIE_ON_ERROR == 'true')" />
		<CONNECTOR CTYPE="ITERATE" MAX_OUTPUT="1" MAX_INPUT="1" />
		<CONNECTOR CTYPE="SUBJOB_OK" MAX_INPUT="1" />
		<CONNECTOR CTYPE="SUBJOB_ERROR" MAX_INPUT="1" />
		<CONNECTOR CTYPE="COMPONENT_OK" />
		<CONNECTOR CTYPE="COMPONENT_ERROR" />
		<CONNECTOR CTYPE="RUN_IF" />
	</CONNECTORS>
	<PARAMETERS>
		<PARAMETER NAME="PROPERTY" FIELD="PROPERTY_TYPE" SHOW_IF="USE_EXISTING_CONNECTION == 'false'"
			NUM_ROW="1" REPOSITORY_VALUE="DATABASE:IMPALA" />

		<PARAMETER NAME="TYPE" FIELD="TEXT" NUM_ROW="3" SHOW="false"
			REPOSITORY_VALUE="TYPE" GROUP="CONNECTION">
			<DEFAULT>Hive</DEFAULT>
		</PARAMETER>

		<!-- CONNECTION PART BEGIN -->

		<PARAMETER NAME="USE_EXISTING_CONNECTION" FIELD="CHECK"
			NUM_ROW="4">
			<DEFAULT>false</DEFAULT>
		</PARAMETER>
		<PARAMETER NAME="CONNECTION" FIELD="COMPONENT_LIST"
			REQUIRED="true" FILTER="tImpalaConnection" NUM_ROW="4"
			SHOW_IF="USE_EXISTING_CONNECTION == 'true'" />

		<PARAMETER NAME="IMPALA" FIELD="HADOOP_DISTRIBUTION"
			NUM_ROW="5" SHOW_IF="USE_EXISTING_CONNECTION=='false'" GROUP="VERSION" />

		<PARAMETER NAME="HADOOP_CUSTOM_JARS" GROUP="VERSION"
			FIELD="HADOOP_JARS_DIALOG" NUM_ROW="5"
			SHOW_IF="(DISTRIBUTION=='CUSTOM' AND USE_EXISTING_CONNECTION=='false')"
			REPOSITORY_VALUE="HADOOP_CUSTOM_JARS">
			<DEFAULT />
		</PARAMETER>

		<PARAMETER NAME="HOST" FIELD="TEXT" NUM_ROW="20"
			REPOSITORY_VALUE="SERVER_NAME" GROUP="CONNECTION"
			SHOW_IF="USE_EXISTING_CONNECTION=='false'">
			<DEFAULT>""</DEFAULT>
		</PARAMETER>

		<PARAMETER NAME="PORT" FIELD="TEXT" NUM_ROW="20"
			REPOSITORY_VALUE="PORT" GROUP="CONNECTION" SHOW_IF="USE_EXISTING_CONNECTION=='false'">
			<DEFAULT>"21050"</DEFAULT>
		</PARAMETER>

		<PARAMETER NAME="USER" FIELD="TEXT" NUM_ROW="25" REPOSITORY_VALUE="USERNAME" GROUP="CONNECTION"
			SHOW_IF="USE_EXISTING_CONNECTION=='false'">
			<DEFAULT>""</DEFAULT>
		</PARAMETER>

		<PARAMETER NAME="PASS" FIELD="TEXT" NUM_ROW="30" GROUP="CONNECTION"
			SHOW="false">
			<DEFAULT>""</DEFAULT>
		</PARAMETER>

		<PARAMETER NAME="DBNAME" FIELD="TEXT" NUM_ROW="30"
			REPOSITORY_VALUE="SID" REQUIRED="true" GROUP="CONNECTION"
			SHOW_IF="USE_EXISTING_CONNECTION=='false'">
			<DEFAULT>"default"</DEFAULT>
		</PARAMETER>

		<PARAMETER NAME="USE_KRB" FIELD="CHECK" NUM_ROW="35"
			REQUIRED="true" REPOSITORY_VALUE="USE_KRB" GROUP="AUTHENTICATION"
			SHOW_IF="USE_EXISTING_CONNECTION=='false'">
			<DEFAULT>false</DEFAULT>
		</PARAMETER>

		<PARAMETER NAME="IMPALA_PRINCIPAL" FIELD="TEXT" NUM_ROW="40"
			REQUIRED="true" REPOSITORY_VALUE="IMPALA_PRINCIPAL" GROUP="AUTHENTICATION"
			SHOW_IF="(isShow[USE_KRB]) AND USE_KRB=='true'">
			<DEFAULT>"impala/_HOST@EXAMPLE.COM"</DEFAULT>
		</PARAMETER>

		<!-- CONNECTION PART END -->

		<!-- LOAD PART BEGIN -->
		<PARAMETER NAME="SCHEMA_FLOW" FIELD="SCHEMA_TYPE" NUM_ROW="60">
			<DEFAULT>""</DEFAULT>
		</PARAMETER>

		<PARAMETER NAME="SCHEMA_REJECT" FIELD="SCHEMA_TYPE"
			REQUIRED="true" NUM_ROW="60" CONTEXT="REJECT" SHOW="true">
			<TABLE READONLY="true">
				<COLUMN NAME="errorCode" TYPE="id_String" LENGTH="255"
					READONLY="false" CUSTOM="true" />
				<COLUMN NAME="errorMessage" TYPE="id_String" LENGTH="255"
					READONLY="false" CUSTOM="true" />
			</TABLE>
		</PARAMETER>

		<PARAMETER NAME="TABLE" FIELD="DBTABLE" NUM_ROW="60">
			<DEFAULT>""</DEFAULT>
		</PARAMETER>

		<PARAMETER NAME="QUERYSTORE" FIELD="QUERYSTORE_TYPE"
			NUM_ROW="70">
			<DEFAULT>""</DEFAULT>
		</PARAMETER>

		<PARAMETER NAME="QUERY" FIELD="MEMO_SQL" NUM_ROW="80">
			<DEFAULT>"select id, name from employee"</DEFAULT>
		</PARAMETER>

		<PARAMETER NAME="DIE_ON_ERROR" FIELD="CHECK" NUM_ROW="90">
			<DEFAULT>false</DEFAULT>
		</PARAMETER>
		<!-- LOAD PART END -->
	</PARAMETERS>

	<ADVANCED_PARAMETERS>
		<PARAMETER NAME="PROPAGATE_RECORD_SET" FIELD="CHECK"
			NUM_ROW="5">
			<DEFAULT>false</DEFAULT>
		</PARAMETER>

		<PARAMETER NAME="RECORD_SET_COLUMN" FIELD="COLUMN_LIST"
			NUM_ROW="5"
			SHOW_IF="(isShow[PROPAGATE_RECORD_SET]) AND (PROPAGATE_RECORD_SET == 'true')" />

		<PARAMETER NAME="ENCODING" FIELD="ENCODING_TYPE" NUM_ROW="9"
			REQUIRED="true" SHOW="false">
			<DEFAULT>"ISO-8859-15"</DEFAULT>
		</PARAMETER>
	</ADVANCED_PARAMETERS>
	<CODEGENERATION>
		<IMPORTS>
			<IMPORT NAME="hadoop-conf-kerberos" MODULE="hadoop-conf-kerberos.jar"
				MVN="mvn:org.talend.libraries/hadoop-conf-kerberos/6.0.0"
				UrlPath="platform:/plugin/org.talend.libraries.hadoop.mapr2/lib/hadoop-conf-kerberos.jar"
				REQUIRED_IF="(USE_EXISTING_CONNECTION=='false' AND DISTRIBUTION!='CUSTOM' AND USE_KRB=='true')" />
			<IMPORT NAME="commons-logging-1.1.3.jar" MODULE="commons-logging-1.1.3.jar"
				MVN="mvn:org.talend.libraries/commons-logging-1.1.3/6.0.0"
				UrlPath="platform:/plugin/org.talend.libraries.apache.common/lib/commons-logging-1.1.3.jar"
				REQUIRED_IF="(IMPALA_VERSION=='Cloudera_CDH5_1' AND DISTRIBUTION!='CUSTOM' AND USE_EXISTING_CONNECTION=='false')"
				BundleID="" />
			<IMPORT NAME="hive-common-0.12.0-cdh5.1.2.jar" MODULE="hive-common-0.12.0-cdh5.1.2.jar"
				MVN="mvn:org.talend.libraries/hive-common-0.12.0-cdh5.1.2/6.0.0"
				UrlPath="platform:/plugin/org.talend.libraries.hadoop.cloudera.cdh5.1/lib/hive-common-0.12.0-cdh5.1.2.jar"
				REQUIRED_IF="(IMPALA_VERSION=='Cloudera_CDH5_1' AND DISTRIBUTION!='CUSTOM' AND USE_EXISTING_CONNECTION=='false')" />
			<IMPORT NAME="hadoop-common-2.3.0-cdh5.1.2.jar" MODULE="hadoop-common-2.3.0-cdh5.1.2.jar"
				MVN="mvn:org.talend.libraries/hadoop-common-2.3.0-cdh5.1.2/6.0.0"
				UrlPath="platform:/plugin/org.talend.libraries.hadoop.cloudera.cdh5.1/lib/hadoop-common-2.3.0-cdh5.1.2.jar"
				REQUIRED_IF="(IMPALA_VERSION=='Cloudera_CDH5_1' AND DISTRIBUTION!='CUSTOM' AND USE_EXISTING_CONNECTION=='false')" />
			<IMPORT NAME="hive-jdbc-0.12.0-cdh5.1.2.jar" MODULE="hive-jdbc-0.12.0-cdh5.1.2.jar"
				MVN="mvn:org.talend.libraries/hive-jdbc-0.12.0-cdh5.1.2/6.0.0"
				UrlPath="platform:/plugin/org.talend.libraries.hadoop.cloudera.cdh5.1/lib/hive-jdbc-0.12.0-cdh5.1.2.jar"
				REQUIRED_IF="(IMPALA_VERSION=='Cloudera_CDH5_1' AND DISTRIBUTION!='CUSTOM' AND USE_EXISTING_CONNECTION=='false')" />
			<IMPORT NAME="hive-metastore-0.12.0-cdh5.1.2.jar" MODULE="hive-metastore-0.12.0-cdh5.1.2.jar"
				MVN="mvn:org.talend.libraries/hive-metastore-0.12.0-cdh5.1.2/6.0.0"
				UrlPath="platform:/plugin/org.talend.libraries.hadoop.cloudera.cdh5.1/lib/hive-metastore-0.12.0-cdh5.1.2.jar"
				REQUIRED_IF="(IMPALA_VERSION=='Cloudera_CDH5_1' AND DISTRIBUTION!='CUSTOM' AND USE_EXISTING_CONNECTION=='false')" />
			<IMPORT NAME="hive-service-0.12.0-cdh5.1.2.jar" MODULE="hive-service-0.12.0-cdh5.1.2.jar"
				MVN="mvn:org.talend.libraries/hive-service-0.12.0-cdh5.1.2/6.0.0"
				UrlPath="platform:/plugin/org.talend.libraries.hadoop.cloudera.cdh5.1/lib/hive-service-0.12.0-cdh5.1.2.jar"
				REQUIRED_IF="(IMPALA_VERSION=='Cloudera_CDH5_1' AND DISTRIBUTION!='CUSTOM' AND USE_EXISTING_CONNECTION=='false')" />
			<IMPORT NAME="httpcore-4.1.3.jar" MODULE="httpcore-4.1.3.jar"
				MVN="mvn:org.talend.libraries/httpcore-4.1.3/6.0.0"
				REQUIRED_IF="(IMPALA_VERSION=='Cloudera_CDH5_1' AND DISTRIBUTION!='CUSTOM' AND USE_EXISTING_CONNECTION=='false')" />
			<IMPORT NAME="httpclient-4.2.5.jar" MODULE="httpclient-4.2.5.jar"
				MVN="mvn:org.talend.libraries/httpclient-4.2.5/6.0.0"
				UrlPath="platform:/plugin/org.talend.libraries.apache.http/lib/httpclient-4.2.5.jar"
				REQUIRED_IF="(IMPALA_VERSION=='Cloudera_CDH5_1' AND DISTRIBUTION!='CUSTOM' AND USE_EXISTING_CONNECTION=='false')" />
			<IMPORT NAME="libfb303-0.9.0.jar" MODULE="libfb303-0.9.0.jar"
				MVN="mvn:org.talend.libraries/libfb303-0.9.0/6.0.0"
				UrlPath="platform:/plugin/org.talend.libraries.hadoop.hdp.1.2/lib/libfb303-0.9.0.jar"
				REQUIRED_IF="(IMPALA_VERSION=='Cloudera_CDH5_1' AND DISTRIBUTION!='CUSTOM' AND USE_EXISTING_CONNECTION=='false')" />
			<IMPORT NAME="libthrift-0.9.0.cloudera.2.jar" MODULE="libthrift-0.9.0.cloudera.2.jar"
				MVN="mvn:org.talend.libraries/libthrift-0.9.0.cloudera.2/6.0.0"
				UrlPath="platform:/plugin/org.talend.libraries.hadoop.cloudera.cdh5/lib/libthrift-0.9.0.cloudera.2.jar"
				REQUIRED_IF="(IMPALA_VERSION=='Cloudera_CDH5_1' AND DISTRIBUTION!='CUSTOM' AND USE_EXISTING_CONNECTION=='false')" />
			<IMPORT NAME="log4j-1.2.17.jar" MODULE="log4j-1.2.17.jar"
				MVN="mvn:org.talend.libraries/log4j-1.2.17/6.0.0"
				UrlPath="platform:/plugin/org.talend.libraries.apache/lib/log4j-1.2.17.jar"
				REQUIRED_IF="(IMPALA_VERSION=='Cloudera_CDH5_1' AND DISTRIBUTION!='CUSTOM' AND USE_EXISTING_CONNECTION=='false')"
				BundleID="" />
			<IMPORT NAME="slf4j-api-1.7.5.jar" MODULE="slf4j-api-1.7.5.jar"
				MVN="mvn:org.talend.libraries/slf4j-api-1.7.5/6.0.0"
				UrlPath="platform:/plugin/org.talend.libraries.slf4j/lib/slf4j-api-1.7.5.jar"
				REQUIRED_IF="(IMPALA_VERSION=='Cloudera_CDH5_1' AND DISTRIBUTION!='CUSTOM' AND USE_EXISTING_CONNECTION=='false')"
				BundleID="" />
			<IMPORT NAME="slf4j-log4j12-1.7.5.jar" MODULE="slf4j-log4j12-1.7.5.jar"
				MVN="mvn:org.talend.libraries/slf4j-log4j12-1.7.5/6.0.0"
				UrlPath="platform:/plugin/org.talend.libraries.slf4j/lib/slf4j-log4j12-1.7.5.jar"
				REQUIRED_IF="(IMPALA_VERSION=='Cloudera_CDH5_1' AND DISTRIBUTION!='CUSTOM' AND USE_EXISTING_CONNECTION=='false')"
				BundleID="" />

			<!-- Cloudera_CDH5_4 -->
			<IMPORT MODULE_GROUP="IMPALA-LIB-CDH_5_4_LASTEST"
				REQUIRED_IF="(IMPALA_VERSION=='Cloudera_CDH5_4' AND DISTRIBUTION!='CUSTOM' AND USE_EXISTING_CONNECTION=='false')" />
		</IMPORTS>
	</CODEGENERATION>
	<RETURNS>
		<RETURN NAME="QUERY" TYPE="id_String" AVAILABILITY="FLOW" />
	</RETURNS>
</COMPONENT>
